topsis/102003404.py
topsis/__init__.py
Topsis_Parush_102003404-0.2.dist-info/LICENSE.txt
Topsis_Parush_102003404-0.2.dist-info/METADATA
Topsis_Parush_102003404-0.2.dist-info/WHEEL
Topsis_Parush_102003404-0.2.dist-info/entry_points.txt
Topsis_Parush_102003404-0.2.dist-info/top_level.txt
Topsis_Parush_102003404-0.2.dist-info/RECORD
